{
    "posts": [{"id":1,"title":"brand sexy e-markets","area":"Software Quality","progress":"Not Started","user_name":"Kirsteni Insley"},
    {"id":2,"title":"seize frictionless experiences","area":"Software Quality","progress":"Completed","user_name":"Carine Lockett"},
    {"id":3,"title":"whiteboard B2C markets","area":"R+D","progress":"Not Started","user_name":"Palm McOrkill"},
    {"id":4,"title":"morph cross-media paradigms","area":"R+D","progress":"In Progress","user_name":"Stavros Prudham"},
    {"id":5,"title":"evolve next-generation e-markets","area":"Software Quality","progress":"Not Started","user_name":"Bertrand Fitchet"},
    {"id":6,"title":"drive dot-com markets","area":"Software Quality","progress":"Completed","user_name":"Clea Pott"},
    {"id":7,"title":"reintermediate open-source vortals","area":"R+D","progress":"In Progress","user_name":"Rosamund Kimbling"},
    {"id":8,"title":"optimize out-of-the-box mindshare","area":"POS Platform","progress":"Not Started","user_name":"Crissie Greswell"},
    {"id":9,"title":"strategize holistic ROI","area":"Software Quality","progress":"Completed","user_name":"Ninnette Simonnet"},
    {"id":10,"title":"reinvent web-enabled relationships","area":"POS Platform","progress":"In Progress","user_name":"Fernando Dufour"}]
}